[
    {
        "key": "dbln",
        "value": "%7B%2261560177970981%22%3A%22EuDzDyYi%22%7D",
        "domain": "facebook.com",
        "path": "/login/device-based/",
        "hostOnly": false,
        "creation": "2024-06-05T11:38:21.053Z",
        "lastAccessed": "2024-06-05T11:38:21.054Z"
    },
    {
        "key": "datr",
        "value": "BUBYZjrvl57nN1BUiXv-kXUz",
        "domain": "facebook.com",
        "path": "/",
        "hostOnly": false,
        "creation": "2024-06-05T11:38:21.054Z",
        "lastAccessed": "2024-06-05T11:38:21.054Z"
    },
    {
        "key": "sb",
        "value": "BUBYZrX2CkiKcV4Ljgy5cgTO",
        "domain": "facebook.com",
        "path": "/",
        "hostOnly": false,
        "creation": "2024-06-05T11:38:21.054Z",
        "lastAccessed": "2024-06-05T11:38:21.054Z"
    },
    {
        "key": "ps_n",
        "value": "1",
        "domain": "facebook.com",
        "path": "/",
        "hostOnly": false,
        "creation": "2024-06-05T11:38:21.054Z",
        "lastAccessed": "2024-06-05T11:38:21.054Z"
    },
    {
        "key": "ps_l",
        "value": "1",
        "domain": "facebook.com",
        "path": "/",
        "hostOnly": false,
        "creation": "2024-06-05T11:38:21.054Z",
        "lastAccessed": "2024-06-05T11:38:21.054Z"
    },
    {
        "key": "vpd",
        "value": "v1%3B652x412x2.625",
        "domain": "facebook.com",
        "path": "/",
        "hostOnly": false,
        "creation": "2024-06-05T11:38:21.054Z",
        "lastAccessed": "2024-06-05T11:38:21.054Z"
    },
    {
        "key": "locale",
        "value": "en_GB",
        "domain": "facebook.com",
        "path": "/",
        "hostOnly": false,
        "creation": "2024-06-05T11:38:21.054Z",
        "lastAccessed": "2024-06-05T11:38:21.054Z"
    },
    {
        "key": "wd",
        "value": "412x652",
        "domain": "facebook.com",
        "path": "/",
        "hostOnly": false,
        "creation": "2024-06-05T11:38:21.054Z",
        "lastAccessed": "2024-06-05T11:38:21.054Z"
    },
    {
        "key": "fr",
        "value": "0hbAQiJsn0dsj6GMs.AWUbsEqPArSKLlOcVdn2_6lrvoc.BmWEAF..AAA.0.0.BmYChR.AWWTQz0ip4Y",
        "domain": "facebook.com",
        "path": "/",
        "hostOnly": false,
        "creation": "2024-06-05T11:38:21.054Z",
        "lastAccessed": "2024-06-05T11:38:21.054Z"
    },
    {
        "key": "c_user",
        "value": "61560177970981",
        "domain": "facebook.com",
        "path": "/",
        "hostOnly": false,
        "creation": "2024-06-05T11:38:21.054Z",
        "lastAccessed": "2024-06-05T11:38:21.054Z"
    },
    {
        "key": "xs",
        "value": "14%3An7UDyjTXzXsOEg%3A2%3A1717577809%3A-1%3A-1",
        "domain": "facebook.com",
        "path": "/",
        "hostOnly": false,
        "creation": "2024-06-05T11:38:21.054Z",
        "lastAccessed": "2024-06-05T11:38:21.054Z"
    },
    {
        "key": "fbl_st",
        "value": "101635664%3BT%3A28626458",
        "domain": "facebook.com",
        "path": "/",
        "hostOnly": false,
        "creation": "2024-06-05T11:38:21.054Z",
        "lastAccessed": "2024-06-05T11:38:21.054Z"
    },
    {
        "key": "wl_cbv",
        "value": "v2%3Bclient_version%3A2521%3Btimestamp%3A1717587495",
        "domain": "facebook.com",
        "path": "/",
        "hostOnly": false,
        "creation": "2024-06-05T11:38:21.054Z",
        "lastAccessed": "2024-06-05T11:38:21.054Z"
    }
] 